{
    "Version": "2012-10-17",
    "Statement": [
        {
            "Sid": "BlogDynamoDBAccess",
            "Effect": "Allow",
            "Action": [
                "dynamodb:GetItem",
                "dynamodb:PutItem",
                "dynamodb:UpdateItem",
                "dynamodb:DeleteItem",
                "dynamodb:Query",
                "dynamodb:Scan",
                "dynamodb:BatchGetItem",
                "dynamodb:BatchWriteItem",
                "dynamodb:DescribeTable"
            ],
            "Resource": [
                "arn:aws:dynamodb:us-east-2:435656520815:table/sway-blog-use2",
                "arn:aws:dynamodb:us-east-2:435656520815:table/sway-blog-use2/index/*"
            ]
        },
        {
            "Sid": "NewsletterDynamoDBAccess",
            "Effect": "Allow",
            "Action": [
                "dynamodb:GetItem",
                "dynamodb:PutItem",
                "dynamodb:UpdateItem",
                "dynamodb:DeleteItem",
                "dynamodb:Query",
                "dynamodb:Scan",
                "dynamodb:BatchGetItem",
                "dynamodb:BatchWriteItem",
                "dynamodb:DescribeTable"
            ],
            "Resource": [
                "arn:aws:dynamodb:us-east-2:435656520815:table/sway-news-use2",
                "arn:aws:dynamodb:us-east-2:435656520815:table/sway-news-use2/index/*"
            ]
        },
        {
            "Sid": "DynamoDBListTables",
            "Effect": "Allow",
            "Action": [
                "dynamodb:ListTables"
            ],
            "Resource": "*"
        }
    ]
}
